<?xml version="1.0" encoding="UTF-8" ?>
<odoo>
    <record id="module_category_contact_partner_type" model="ir.module.category">
        <field name="name">Contact Partner Type</field>
        <field name="sequence">20</field>
    </record>

    <record id="group_contact_customer" model="res.groups">
        <field name="name">Customer Access</field>
        <field name="category_id"
               ref="gb_contact_partner_type.module_category_contact_partner_type"/>
    </record>

    <record id="group_contact_supplier" model="res.groups">
        <field name="name">Supplier Access</field>
        <field name="category_id"
               ref="gb_contact_partner_type.module_category_contact_partner_type"/>
    </record>

</odoo>